fk_net/__init__.py
fk_net/errors.py
fk_net/freekassa.py
fk_net/notification.py
fk_net-0.1.1.dist-info/licenses/LICENSE
fk_net-0.1.1.dist-info/METADATA
fk_net-0.1.1.dist-info/WHEEL
fk_net-0.1.1.dist-info/top_level.txt
fk_net-0.1.1.dist-info/RECORD
