Metadata-Version: 2.4
Name: fk-net
Version: 0.1.1
Summary: Library for using service https://docs.freekassa.net/
Home-page: https://github.com/bekjonbegmatov/FK-Net
Author: Bekjon Begmatov
Author-email: behruz@begmatov.dev
Project-URL: Bug Tracker, https://github.com/bekjonbegmatov/FK-Net/issues
Classifier: Programming Language :: Python :: 3.11
Classifier: License :: OSI Approved :: MIT License
Classifier: Operating System :: OS Independent
Requires-Python: >=3.7
License-File: LICENSE
Dynamic: license-file
